line_profiler_decorator/__init__.py
line_profiler_decorator/line_profiler_decorator.py
line_profiler_decorator-0.0.6.dist-info/METADATA
line_profiler_decorator-0.0.6.dist-info/WHEEL
line_profiler_decorator-0.0.6.dist-info/top_level.txt
line_profiler_decorator-0.0.6.dist-info/RECORD
