Metadata-Version: 2.1
Name: line-profiler-decorator
Version: 0.0.6
Summary: Line profiler Output time usage per line
Home-page: https://github.com/nano-labs/line-profiler-decorator
Download-URL: https://github.com/nano-labs/line-profiler-decorator/archive/refs/tags/0.0.6.zip
Author: Fabio Pachelli Pacheco
Author-email: nanook.labs@gmail.com
License: MIT
Keywords: line time profiler decorator
Classifier: Development Status :: 3 - Alpha
Classifier: Intended Audience :: Developers
Classifier: Topic :: Software Development :: Build Tools
Classifier: License :: OSI Approved :: MIT License
Classifier: Programming Language :: Python :: 3.6
Requires-Python: >3.6.0
Requires-Dist: line-profiler (==3.5.1)
